sprocket/__init__.py
sprocket/model/GMM.py
sprocket/model/__init__.py
sprocket/model/diagGMM.py
sprocket/model/f0statistics.py
sprocket/model/gv.py
sprocket/model/ms.py
sprocket/speech/__init__.py
sprocket/speech/analyzer.py
sprocket/speech/feature_extractor.py
sprocket/speech/parameterizer.py
sprocket/speech/shifter.py
sprocket/speech/synthesizer.py
sprocket/speech/wsola.py
sprocket/speech/tests/__init__.py
sprocket/speech/tests/test_acousticfeature.py
sprocket/speech/tests/test_modpower.py
sprocket/speech/tests/test_shifter.py
sprocket/speech/tests/test_wsola.py
sprocket/util/__init__.py
sprocket/util/delta.py
sprocket/util/distance.py
sprocket/util/extfrm.py
sprocket/util/filter.py
sprocket/util/hdf5.py
sprocket/util/twf.py
sprocket/util/tests/__init__.py
sprocket/util/tests/test_delta.py
sprocket/util/tests/test_filter.py
sprocket/util/tests/test_hdf5.py
sprocket/util/tests/test_melcd.py
sprocket_vc-0.18.4.dist-info/LICENSE.txt
sprocket_vc-0.18.4.dist-info/METADATA
sprocket_vc-0.18.4.dist-info/WHEEL
sprocket_vc-0.18.4.dist-info/top_level.txt
sprocket_vc-0.18.4.dist-info/RECORD
