Metadata-Version: 2.1
Name: sprocket-vc
Version: 0.18.4
Summary: Voice conversion software
Home-page: https://github.com/k2kobayashi/sprocket
Author: Kazuhiro Kobayashi
Author-email: root.4mac@gmail.com
License: MIT
Platform: UNKNOWN
Classifier: License :: OSI Approved :: MIT License
Classifier: Topic :: Multimedia :: Sound/Audio :: Speech
Requires-Python: >=3.5
Requires-Dist: scipy
Requires-Dist: pysptk (>=0.1.7)
Requires-Dist: scikit-learn
Requires-Dist: scikit-image
Requires-Dist: pyworld
Requires-Dist: h5py
Requires-Dist: dtw
Requires-Dist: fastdtw
Requires-Dist: pyyaml
Requires-Dist: dtw-c
Requires-Dist: docopt
Provides-Extra: develop
Requires-Dist: nose ; extra == 'develop'
